pactman/__init__.py
pactman/__version__.py
pactman/mock/__init__.py
pactman/mock/consumer.py
pactman/mock/matchers.py
pactman/mock/mock_server.py
pactman/mock/mock_urlopen.py
pactman/mock/pact.py
pactman/mock/pact_request_handler.py
pactman/mock/provider.py
pactman/mock/request.py
pactman/mock/response.py
pactman/test/__init__.py
pactman/test/test_matching_rules.py
pactman/test/test_mock_consumer.py
pactman/test/test_mock_matchers.py
pactman/test/test_mock_pact.py
pactman/test/test_mock_provider.py
pactman/test/test_mock_request.py
pactman/test/test_mock_response.py
pactman/test/test_mock_urlopen.py
pactman/test/test_pact_generation.py
pactman/test/test_parse_header.py
pactman/test/test_result.py
pactman/test/test_verifier.py
pactman/verifier/__init__.py
pactman/verifier/broker_pact.py
pactman/verifier/command_line.py
pactman/verifier/matching_rule.py
pactman/verifier/parse_header.py
pactman/verifier/paths.py
pactman/verifier/pytest_plugin.py
pactman/verifier/result.py
pactman/verifier/verify.py
pactman-2.6.1.dist-info/LICENSE
pactman-2.6.1.dist-info/METADATA
pactman-2.6.1.dist-info/WHEEL
pactman-2.6.1.dist-info/entry_points.txt
pactman-2.6.1.dist-info/top_level.txt
pactman-2.6.1.dist-info/RECORD
