Metadata-Version: 2.1
Name: pactman
Version: 2.6.1
Summary: Tools for creating and verifying consumer driven contracts using the Pact framework.
Home-page: https://github.com/reecetech/pactman
Author: ReeceTech
Author-email: richard.jones@reece.com.au
License: MIT, Copyright (c) 2018 ReeceTech
Platform: UNKNOWN
Classifier: Intended Audience :: Developers
Classifier: License :: OSI Approved :: MIT License
Classifier: Programming Language :: Python :: 3
Classifier: Programming Language :: Python :: 3.6
Classifier: Topic :: Software Development :: Testing
Classifier: Topic :: Software Development :: Testing :: Mocking
Classifier: Topic :: Software Development :: Testing :: Acceptance
Requires-Dist: pytest
Requires-Dist: requests
Requires-Dist: semver
Requires-Dist: colorama
Requires-Dist: restnavigator
